mendeley_cli/__init__.py
mendeley_cli-0.3.0.dist-info/LICENSE
mendeley_cli-0.3.0.dist-info/METADATA
mendeley_cli-0.3.0.dist-info/WHEEL
mendeley_cli-0.3.0.dist-info/entry_points.txt
mendeley_cli-0.3.0.dist-info/top_level.txt
mendeley_cli-0.3.0.dist-info/RECORD
