Metadata-Version: 2.1
Name: mendeley-cli
Version: 0.3.0
Summary: Mendeley CLI
Home-page: https://github.com/shuichiro-makigaki/mendeley_cli
Author: Shuichiro MAKIGAKI
Author-email: shuichiro.makigaki@gmail.com
License: MIT
Platform: UNKNOWN
License-File: LICENSE
Requires-Dist: requests
Requires-Dist: yandeley
Requires-Dist: click
Requires-Dist: tablib[all]
Requires-Dist: python-dotenv
Requires-Dist: colr
